Metadata-Version: 1.1
Name: pyfarm.agent
Version: 0.8.6
Summary: Core module containing code to run PyFarm's agent.
Home-page: https://github.com/pyfarm/pyfarm-agent
Author: Oliver Palmer
Author-email: development@pyfarm.net
License: Apache v2.0
Platform: UNKNOWN
Classifier: Development Status :: 2 - Pre-Alpha
Classifier: Environment :: No Input/Output (Daemon)
Classifier: License :: OSI Approved :: Apache Software License
Classifier: Natural Language :: English
Classifier: Operating System :: OS Independent
Classifier: Programming Language :: Python :: 2.6
Classifier: Programming Language :: Python :: 2.7
Classifier: Topic :: System :: Distributed Computing
